Metadata-Version: 1.1
Name: smallshapes
Version: 0.6.0
Summary: A simple engine that implements mathematical shapes of small dimensionality
Home-page: UNKNOWN
Author: Fábio Macêdo Mendes
Author-email: fabiomacedomendes@gmail.com
License: UNKNOWN
Platform: any
Classifier: Development Status :: 3 - Alpha
Classifier: Intended Audience :: Developers
Classifier: License :: OSI Approved :: GNU General Public License (GPL)
Classifier: Operating System :: POSIX
Classifier: Programming Language :: Python
Classifier: Programming Language :: Python :: 3.3
Classifier: Programming Language :: Python :: 3.4
Classifier: Programming Language :: Python :: 3.5
Classifier: Topic :: Software Development :: Libraries
